setup.py
probability_distributions99/Binomialdistribution.py
probability_distributions99/Gaussiandistribution.py
probability_distributions99/Generaldistribution.py
probability_distributions99/__init__.py
probability_distributions99.egg-info/PKG-INFO
probability_distributions99.egg-info/SOURCES.txt
probability_distributions99.egg-info/dependency_links.txt
probability_distributions99.egg-info/not-zip-safe
probability_distributions99.egg-info/top_level.txt